htk_django_dbshell_plus/__init__.py
htk_django_dbshell_plus/management/__init__.py
htk_django_dbshell_plus/management/commands/__init__.py
htk_django_dbshell_plus/management/commands/dbshell_plus.py
htk_django_dbshell_plus-2.0.2.dist-info/AUTHORS.md
htk_django_dbshell_plus-2.0.2.dist-info/LICENSE
htk_django_dbshell_plus-2.0.2.dist-info/METADATA
htk_django_dbshell_plus-2.0.2.dist-info/WHEEL
htk_django_dbshell_plus-2.0.2.dist-info/top_level.txt
htk_django_dbshell_plus-2.0.2.dist-info/RECORD
