Metadata-Version: 2.1
Name: htk-django-dbshell-plus
Version: 2.0.2
Summary: A dbshell_plus management command for Django that selects pgcli or mycli when available.
Home-page: https://github.com/hacktoolkit/django-dbshell-plus
Author: Hacktoolkit
Author-email: hello@hacktoolkit.com
License: BSD
Keywords: htk-django-dbshell-plus
Platform: UNKNOWN
Classifier: Development Status :: 2 - Pre-Alpha
Classifier: Intended Audience :: Developers
Classifier: License :: OSI Approved :: BSD License
Classifier: Natural Language :: English
Classifier: Programming Language :: Python :: 3
License-File: LICENSE
License-File: AUTHORS.md
Requires-Dist: Django
